dilivia_data_client/__init__.py
dilivia_data_client/connexion/__init__.py
dilivia_data_client/mapping_dilivia.py
dilivia_data_client/query.py
dilivia_data_client-0.1.6.dist-info/LICENSE
dilivia_data_client-0.1.6.dist-info/WHEEL
dilivia_data_client-0.1.6.dist-info/METADATA
dilivia_data_client-0.1.6.dist-info/RECORD
