Metadata-Version: 2.1
Name: dilivia-data-client
Version: 0.1.6
Summary: 
Home-page: https://www.dilivia.net/
Author: dilivia.enovea
Author-email: contact@dilivia.net
Maintainer: martin.nivon
Maintainer-email: martin.nivon@enovea.net
Requires-Python: >=3.8,<4.0
Classifier: Programming Language :: Python :: 3
Classifier: Programming Language :: Python :: 3.10
Classifier: Programming Language :: Python :: 3.8
Classifier: Programming Language :: Python :: 3.9
Requires-Dist: numpy (>=1.22.1,<2.0.0)
Requires-Dist: pandas (==1.4.0)
Requires-Dist: pydruid (>=0.6.2,<0.7.0)
Requires-Dist: pylint (>=2.12.2,<3.0.0)
Requires-Dist: python-dateutil (>=2.8.2,<3.0.0)
Requires-Dist: pytz (>=2021.3,<2022.0)
Requires-Dist: requests (>=2.27.1,<3.0.0)
Project-URL: Documentation, https://www.dilivia.net/posts/
